webmixer/__init__.py
webmixer/exceptions.py
webmixer/messages.py
webmixer/utils.py
webmixer/scrapers/__init__.py
webmixer/scrapers/base.py
webmixer/scrapers/tags.py
webmixer/scrapers/pages/__init__.py
webmixer/scrapers/pages/audio.py
webmixer/scrapers/pages/base.py
webmixer/scrapers/pages/gdrive.py
webmixer/scrapers/pages/misc.py
webmixer/scrapers/pages/presentations.py
webmixer/scrapers/pages/wikipedia.py
webmixer-0.0.0.dist-info/AUTHORS.rst
webmixer-0.0.0.dist-info/LICENSE
webmixer-0.0.0.dist-info/METADATA
webmixer-0.0.0.dist-info/WHEEL
webmixer-0.0.0.dist-info/top_level.txt
webmixer-0.0.0.dist-info/RECORD
