Metadata-Version: 2.1
Name: webmixer
Version: 0.0.0
Summary: Library for scraping urls and downloading them as files
Home-page: https://github.com/learningequality/webmixer
Author: Learning Equality
Author-email: dev@learningequality.org
License: MIT
Download-URL: https://github.com/learningequality/webmixer/releases
Keywords: scrapers webmixer web-mixer mixer scraper
Platform: UNKNOWN
Classifier: Development Status :: 3 - Alpha
Classifier: Intended Audience :: Developers
Classifier: License :: OSI Approved :: MIT License
Classifier: Natural Language :: English
Classifier: Programming Language :: Python :: 3.4
Classifier: Programming Language :: Python :: 3.5
Requires-Dist: requests (>=2.11.1)
Requires-Dist: beautifulsoup4 (>=4.6.3)
Requires-Dist: ricecooker (>=0.6.31)
Requires-Dist: le-utils (>=0.1.19)
Requires-Dist: cssutils (>=1.0.2)
Requires-Dist: google-api-python-client (>=1.7.9)
Requires-Dist: google-auth-oauthlib (>=0.4.0)
Requires-Dist: oauthlib (>=3.0.1)
Requires-Dist: requests-oauthlib (>=1.2.0)
Requires-Dist: youtube-dl (>=2019.7.2)
